[
    {
        "TrialAvatarId": 1,
        "TrialAvatarParam": [
            10000021,
            5
        ],
        "TrialWeaponParam": [
            15201,
            5
        ],
        "TrialSkillDepotId": 1
    },
    {
        "TrialAvatarId": 2,
        "TrialAvatarParam": [
            10000015,
            5
        ],
        "TrialWeaponParam": [
            11201,
            5
        ],
        "TrialSkillDepotId": 1
    },
    {
        "TrialAvatarId": 3,
        "TrialAvatarParam": [
            10000006,
            5
        ],
        "TrialWeaponParam": [
            14201,
            5
        ],
        "TrialSkillDepotId": 1
    },
    {
        "TrialAvatarId": 4,
        "TrialAvatarParam": [
            10000016,
            23
        ],
        "TrialWeaponParam": [
            12401,
            23
        ],
        "TrialSkillDepotId": 1
    },
    {
        "TrialAvatarId": 5,
        "TrialAvatarParam": [
            10000022,
            26
        ],
        "TrialWeaponParam": [
            15301,
            26
        ],
        "TrialSkillDepotId": 1
    },
    {
        "TrialAvatarId": 6,
        "TrialAvatarParam": [
            10000015,
            10
        ],
        "TrialWeaponParam": [
            11301,
            10
        ],
        "TrialSkillDepotId": 1
    },
    {
        "TrialAvatarId": 7,
        "TrialAvatarParam": [
            10000003,
            30
        ],
        "TrialWeaponParam": [
            11401,
            30
        ],
        "TrialSkillDepotId": 1
    },
    {
        "TrialAvatarId": 8,
        "TrialAvatarParam": [
            10000021,
            15
        ],
        "TrialWeaponParam": [
            15301,
            15
        ],
        "TrialSkillDepotId": 1
    },
    {
        "TrialAvatarId": 9,
        "TrialAvatarParam": [
            10000020,
            26
        ],
        "TrialWeaponParam": [
            12401,
            26
        ],
        "TrialSkillDepotId": 1
    },
    {
        "TrialAvatarId": 10,
        "TrialAvatarParam": [
            10000006,
            19
        ],
        "TrialWeaponParam": [
            14301,
            19
        ],
        "TrialSkillDepotId": 1
    },
    {
        "TrialAvatarId": 11,
        "TrialAvatarParam": [
            10000016,
            18
        ],
        "TrialWeaponParam": [
            12401,
            18
        ],
        "TrialSkillDepotId": 1
    },
    {
        "TrialAvatarId": 12,
        "TrialAvatarParam": [
            10000025,
            26
        ],
        "TrialWeaponParam": [
            11406,
            26
        ],
        "TrialSkillDepotId": 1
    },
    {
        "TrialAvatarId": 13,
        "TrialAvatarParam": [
            10000023,
            16
        ],
        "TrialWeaponParam": [
            13301,
            16
        ],
        "TrialSkillDepotId": 1
    },
    {
        "TrialAvatarId": 14,
        "TrialAvatarParam": [
            10000029,
            30
        ],
        "TrialWeaponParam": [
            14401,
            30
        ],
        "TrialSkillDepotId": 1
    },
    {
        "TrialAvatarId": 17,
        "TrialAvatarParam": [
            10000030,
            35
        ],
        "TrialWeaponParam": [
            13504,
            35
        ],
        "TrialSkillDepotId": 1
    },
    {
        "TrialAvatarId": 18,
        "TrialAvatarParam": [
            10000022,
            28
        ],
        "TrialWeaponParam": [
            15401,
            28
        ],
        "TrialSkillDepotId": 1
    },
    {
        "TrialAvatarId": 19,
        "TrialAvatarParam": [
            10000041,
            30
        ],
        "TrialWeaponParam": [
            14501,
            30
        ],
        "TrialSkillDepotId": 1
    },
    {
        "TrialAvatarId": 20,
        "TrialAvatarParam": [
            10000035,
            35
        ],
        "TrialWeaponParam": [
            11501,
            35
        ],
        "TrialSkillDepotId": 1
    },
    {
        "TrialAvatarId": 21,
        "TrialAvatarParam": [
            10000033,
            35
        ],
        "TrialWeaponParam": [
            15501,
            35
        ],
        "TrialSkillDepotId": 1
    },
    {
        "TrialAvatarId": 22,
        "TrialAvatarParam": [
            10000041,
            26
        ],
        "TrialWeaponParam": [
            14501,
            26
        ],
        "TrialSkillDepotId": 1
    },
    {
        "TrialAvatarId": 23,
        "TrialAvatarParam": [
            10000037,
            35
        ],
        "TrialWeaponParam": [
            15501,
            35
        ],
        "TrialSkillDepotId": 1
    },
    {
        "TrialAvatarId": 1003,
        "TrialAvatarParam": [
            10000003,
            80
        ],
        "TrialWeaponParam": [
            11401,
            80
        ]
    },
    {
        "TrialAvatarId": 1004,
        "TrialAvatarParam": [
            10000006,
            80
        ],
        "TrialWeaponParam": [
            14401,
            80
        ]
    },
    {
        "TrialAvatarId": 1014,
        "TrialAvatarParam": [
            10000014,
            80
        ],
        "TrialWeaponParam": [
            14401,
            80
        ]
    },
    {
        "TrialAvatarId": 1015,
        "TrialAvatarParam": [
            10000015,
            80
        ],
        "TrialWeaponParam": [
            11401,
            80
        ]
    },
    {
        "TrialAvatarId": 1016,
        "TrialAvatarParam": [
            10000016,
            80
        ],
        "TrialWeaponParam": [
            12401,
            80
        ]
    },
    {
        "TrialAvatarId": 1020,
        "TrialAvatarParam": [
            10000020,
            80
        ],
        "TrialWeaponParam": [
            12401,
            80
        ]
    },
    {
        "TrialAvatarId": 1021,
        "TrialAvatarParam": [
            10000021,
            80
        ],
        "TrialWeaponParam": [
            15401,
            80
        ]
    },
    {
        "TrialAvatarId": 1022,
        "TrialAvatarParam": [
            10000022,
            80
        ],
        "TrialWeaponParam": [
            15401,
            80
        ]
    },
    {
        "TrialAvatarId": 1023,
        "TrialAvatarParam": [
            10000023,
            80
        ],
        "TrialWeaponParam": [
            13401,
            80
        ]
    },
    {
        "TrialAvatarId": 1024,
        "TrialAvatarParam": [
            10000024,
            80
        ],
        "TrialWeaponParam": [
            12401,
            80
        ]
    },
    {
        "TrialAvatarId": 1025,
        "TrialAvatarParam": [
            10000025,
            80
        ],
        "TrialWeaponParam": [
            11406,
            80
        ]
    },
    {
        "TrialAvatarId": 1027,
        "TrialAvatarParam": [
            10000027,
            80
        ],
        "TrialWeaponParam": [
            14401,
            80
        ]
    },
    {
        "TrialAvatarId": 1029,
        "TrialAvatarParam": [
            10000029,
            80
        ],
        "TrialWeaponParam": [
            14401,
            80
        ]
    },
    {
        "TrialAvatarId": 1030,
        "TrialAvatarParam": [
            10000030,
            80
        ],
        "TrialWeaponParam": [
            13402,
            80
        ]
    },
    {
        "TrialAvatarId": 1031,
        "TrialAvatarParam": [
            10000031,
            80
        ],
        "TrialWeaponParam": [
            15401,
            80
        ]
    },
    {
        "TrialAvatarId": 1032,
        "TrialAvatarParam": [
            10000032,
            80
        ],
        "TrialWeaponParam": [
            11401,
            80
        ]
    },
    {
        "TrialAvatarId": 1033,
        "TrialAvatarParam": [
            10000033,
            80
        ],
        "TrialWeaponParam": [
            15401,
            80
        ]
    },
    {
        "TrialAvatarId": 1034,
        "TrialAvatarParam": [
            10000034,
            80
        ],
        "TrialWeaponParam": [
            12401,
            80
        ]
    },
    {
        "TrialAvatarId": 1035,
        "TrialAvatarParam": [
            10000035,
            80
        ],
        "TrialWeaponParam": [
            11401,
            80
        ]
    },
    {
        "TrialAvatarId": 1036,
        "TrialAvatarParam": [
            10000036,
            80
        ],
        "TrialWeaponParam": [
            12401,
            80
        ]
    },
    {
        "TrialAvatarId": 1037,
        "TrialAvatarParam": [
            10000037,
            80
        ],
        "TrialWeaponParam": [
            15401,
            80
        ]
    },
    {
        "TrialAvatarId": 1038,
        "TrialAvatarParam": [
            10000038,
            80
        ],
        "TrialWeaponParam": [
            11401,
            80
        ]
    },
    {
        "TrialAvatarId": 1039,
        "TrialAvatarParam": [
            10000039,
            80
        ],
        "TrialWeaponParam": [
            15401,
            80
        ]
    },
    {
        "TrialAvatarId": 1041,
        "TrialAvatarParam": [
            10000041,
            80
        ],
        "TrialWeaponParam": [
            14501,
            80
        ]
    },
    {
        "TrialAvatarId": 1042,
        "TrialAvatarParam": [
            10000042,
            80
        ],
        "TrialWeaponParam": [
            11401,
            80
        ]
    },
    {
        "TrialAvatarId": 1043,
        "TrialAvatarParam": [
            10000043,
            80
        ],
        "TrialWeaponParam": [
            14401,
            80
        ]
    },
    {
        "TrialAvatarId": 1044,
        "TrialAvatarParam": [
            10000044,
            80
        ],
        "TrialWeaponParam": [
            12401,
            80
        ]
    },
    {
        "TrialAvatarId": 5000,
        "TrialAvatarParam": [
            10000015,
            20
        ],
        "TrialWeaponParam": [
            11301,
            20
        ]
    },
    {
        "TrialAvatarId": 5001,
        "TrialAvatarParam": [
            10000006,
            20
        ],
        "TrialWeaponParam": [
            14301,
            20
        ]
    },
    {
        "TrialAvatarId": 5002,
        "TrialAvatarParam": [
            10000023,
            20
        ],
        "TrialWeaponParam": [
            13301,
            20
        ]
    },
    {
        "TrialAvatarId": 5003,
        "TrialAvatarParam": [
            10000014,
            20
        ],
        "TrialWeaponParam": [
            14301,
            20
        ]
    },
    {
        "TrialAvatarId": 5004,
        "TrialAvatarParam": [
            10000027,
            20
        ],
        "TrialWeaponParam": [
            14301,
            20
        ]
    },
    {
        "TrialAvatarId": 5005,
        "TrialAvatarParam": [
            10000043,
            20
        ],
        "TrialWeaponParam": [
            14301,
            20
        ]
    }
]